SimpleMDMpy/Account.py
SimpleMDMpy/AppGroups.py
SimpleMDMpy/Apps.py
SimpleMDMpy/AssignmentGroups.py
SimpleMDMpy/CustomAttributes.py
SimpleMDMpy/CustomConfigurationProfiles.py
SimpleMDMpy/DepServers.py
SimpleMDMpy/DeviceGroups.py
SimpleMDMpy/Devices.py
SimpleMDMpy/Enrollments.py
SimpleMDMpy/InstalledApps.py
SimpleMDMpy/Logs.py
SimpleMDMpy/LostMode.py
SimpleMDMpy/ManagedAppConfigs.py
SimpleMDMpy/PushCertificate.py
SimpleMDMpy/ScriptJobs.py
SimpleMDMpy/Scripts.py
SimpleMDMpy/SimpleMDM.py
SimpleMDMpy/__init__.py
SimpleMDMpy-3.0.7.dist-info/LICENSE
SimpleMDMpy-3.0.7.dist-info/METADATA
SimpleMDMpy-3.0.7.dist-info/WHEEL
SimpleMDMpy-3.0.7.dist-info/top_level.txt
SimpleMDMpy-3.0.7.dist-info/RECORD
