Metadata-Version: 2.1
Name: SimpleMDMpy
Version: 3.0.7
Summary: A Python Library for SimpleMDM.
Home-page: https://github.com/macadmins/simpleMDMpy
Author: Steve Küng
Maintainer: MacAdmins
License: MIT
Classifier: Development Status :: 3 - Alpha
Classifier: Intended Audience :: System Administrators
Classifier: License :: OSI Approved :: MIT License
Classifier: Operating System :: OS Independent
Classifier: Programming Language :: Python :: 3
License-File: LICENSE
Requires-Dist: requests
